pdpp_bhi/__init__.py
pdpp_bhi/pdpp_bhi.py
pdpp_bhi-0.0.9.dist-info/METADATA
pdpp_bhi-0.0.9.dist-info/WHEEL
pdpp_bhi-0.0.9.dist-info/top_level.txt
pdpp_bhi-0.0.9.dist-info/RECORD
